{
  "slug": "catherine-colonna",
  "nom": "Colonna",
  "prenom": "Catherine",
  "civilite": "Mme",
  "researched_at": "2026-04-01",
  "_ingested": false,
  "sources_used": [
    "https://www.lemonde.fr/politique/",
    "https://www.diplomatie.gouv.fr/"
  ],
  "notes": "Juriste (Tours), Sciences Po, ENA. Diplomate de carrière: porte-parole de l'Élysée 1995-2004, ministre des Affaires européennes 2005-2007, ambassadrice en Italie, à l'OCDE et au Royaume-Uni. Brunswick Group 2010-2014. Ministre des Affaires étrangères sous Borne 2022-2024.",
  "career_entries": [
    {
      "dateDebut": "1978",
      "dateFin": "1982",
      "categorie": "FORMATION",
      "titre": "Licence de droit",
      "organisation": "Université de Tours",
      "description": "Études de droit.",
      "sourceUrl": "https://www.lemonde.fr/",
      "sourcePrincipale": "Le Monde",
      "sourceDate": "2024",
      "confidence": "high",
      "_ingested": true
    },
    {
      "dateDebut": "1982",
      "dateFin": "1984",
      "categorie": "FORMATION",
      "titre": "Sciences Po Paris + ENA",
      "organisation": "Sciences Po / ENA",
      "description": "Formation à Sciences Po puis à l'ENA.",
      "sourceUrl": "https://www.lemonde.fr/",
      "sourcePrincipale": "Le Monde",
      "sourceDate": "2024",
      "confidence": "high",
      "_ingested": true
    },
    {
      "dateDebut": "1984",
      "dateFin": "1995",
      "categorie": "FONCTION_PUBLIQUE",
      "titre": "Diplomate au Quai d'Orsay",
      "organisation": "Ministère des Affaires étrangères",
      "description": "Début de carrière diplomatique.",
      "sourceUrl": "https://www.diplomatie.gouv.fr/",
      "sourcePrincipale": "MAE",
      "sourceDate": "2024",
      "confidence": "high",
      "_ingested": true
    },
    {
      "dateDebut": "1995",
      "dateFin": "2004",
      "categorie": "FONCTION_PUBLIQUE",
      "titre": "Porte-parole de la présidence de la République",
      "organisation": "Élysée",
      "description": "Porte-parole sous Jacques Chirac.",
      "sourceUrl": "https://www.lemonde.fr/",
      "sourcePrincipale": "Le Monde",
      "sourceDate": "2024",
      "confidence": "high",
      "_ingested": true
    },
    {
      "dateDebut": "2010",
      "dateFin": "2014",
      "categorie": "CARRIERE_PRIVEE",
      "titre": "Associée chez Brunswick Group",
      "organisation": "Brunswick Group",
      "description": "Cabinet de conseil en communication stratégique.",
      "sourceUrl": "https://www.lemonde.fr/",
      "sourcePrincipale": "Le Monde",
      "sourceDate": "2024",
      "confidence": "high",
      "_ingested": true
    },
    {
      "dateDebut": "2014",
      "dateFin": "2017",
      "categorie": "FONCTION_PUBLIQUE",
      "titre": "Ambassadrice de France à l'OCDE",
      "organisation": "OCDE",
      "description": "Représentante permanente de la France auprès de l'OCDE.",
      "sourceUrl": "https://www.diplomatie.gouv.fr/",
      "sourcePrincipale": "MAE",
      "sourceDate": "2024",
      "confidence": "high",
      "_ingested": true
    },
    {
      "dateDebut": "2017",
      "dateFin": "2022",
      "categorie": "FONCTION_PUBLIQUE",
      "titre": "Ambassadrice de France au Royaume-Uni",
      "organisation": "Ambassade de France à Londres",
      "description": "Ambassadrice pendant le Brexit.",
      "sourceUrl": "https://www.diplomatie.gouv.fr/",
      "sourcePrincipale": "MAE",
      "sourceDate": "2024",
      "confidence": "high",
      "_ingested": true
    }
  ],
  "judicial_events": []
}