{
  "slug": "marc-fesneau",
  "nom": "Fesneau",
  "prenom": "Marc",
  "civilite": "M.",
  "researched_at": "2026-04-01",
  "_ingested": false,
  "sources_used": [
    "https://www.assemblee-nationale.fr/"
  ],
  "notes": "DEUG Sciences, Sciences Po. Chambre d'agriculture du Loir-et-Cher. Secretaire general du MoDem. Depute puis ministre de l'Agriculture sous Borne et Attal.",
  "career_entries": [
    {
      "dateDebut": "1990",
      "dateFin": "1995",
      "categorie": "FORMATION",
      "titre": "DEUG Sciences + Sciences Po",
      "organisation": "Universite / Sciences Po",
      "description": "Formation en sciences et sciences politiques.",
      "sourceUrl": "https://www.assemblee-nationale.fr/",
      "sourcePrincipale": "Assemblee nationale",
      "sourceDate": "2024",
      "confidence": "high",
      "_ingested": true
    },
    {
      "dateDebut": "1995",
      "dateFin": "2017",
      "categorie": "CARRIERE_PRIVEE",
      "titre": "Directeur de la chambre d'agriculture du Loir-et-Cher",
      "organisation": "Chambre d'agriculture du Loir-et-Cher",
      "description": "Direction de la chambre d'agriculture. Secretaire general du MoDem.",
      "sourceUrl": "https://www.assemblee-nationale.fr/",
      "sourcePrincipale": "Assemblee nationale",
      "sourceDate": "2024",
      "confidence": "high",
      "_ingested": true
    }
  ],
  "judicial_events": []
}